h2o_notebook/__init__.py
h2o_notebook/exception.py
h2o_notebook/session.py
h2o_notebook/clients/__init__.py
h2o_notebook/clients/connection_config.py
h2o_notebook/clients/login.py
h2o_notebook/clients/auth/__init__.py
h2o_notebook/clients/auth/token_api_client.py
h2o_notebook/clients/base/image_pull_policy.py
h2o_notebook/clients/base/workspace.py
h2o_notebook/clients/convert/__init__.py
h2o_notebook/clients/convert/duration_convertor.py
h2o_notebook/clients/convert/quantity_convertor.py
h2o_notebook/clients/kernel/__init__.py
h2o_notebook/clients/kernel/client.py
h2o_notebook/clients/kernel/kernel.py
h2o_notebook/clients/kernel/kernel_image_info.py
h2o_notebook/clients/kernel/kernel_template_info.py
h2o_notebook/clients/kernel/page.py
h2o_notebook/clients/kernel/state.py
h2o_notebook/clients/kernel/type.py
h2o_notebook/clients/kernel_image/__init__.py
h2o_notebook/clients/kernel_image/client.py
h2o_notebook/clients/kernel_image/kernel_image.py
h2o_notebook/clients/kernel_image/kernel_image_config.py
h2o_notebook/clients/kernel_image/page.py
h2o_notebook/clients/kernel_image/type.py
h2o_notebook/clients/kernel_task/__init__.py
h2o_notebook/clients/kernel_task/client.py
h2o_notebook/clients/kernel_task/kernel_task.py
h2o_notebook/clients/kernel_task/page.py
h2o_notebook/clients/kernel_task/state.py
h2o_notebook/clients/kernel_task_message/__init__.py
h2o_notebook/clients/kernel_task_message/client.py
h2o_notebook/clients/kernel_task_message/display_message.py
h2o_notebook/clients/kernel_task_message/kernel_task_message.py
h2o_notebook/clients/kernel_task_message/page.py
h2o_notebook/clients/kernel_task_output/__init__.py
h2o_notebook/clients/kernel_task_output/client.py
h2o_notebook/clients/kernel_task_output/kernel_task_output.py
h2o_notebook/clients/kernel_template/__init__.py
h2o_notebook/clients/kernel_template/client.py
h2o_notebook/clients/kernel_template/kernel_template.py
h2o_notebook/clients/kernel_template/kernel_template_config.py
h2o_notebook-0.6.4.dist-info/METADATA
h2o_notebook-0.6.4.dist-info/WHEEL
h2o_notebook-0.6.4.dist-info/RECORD
